streamlit_drawable_canvas/__init__.py
streamlit_drawable_canvas/frontend/build/asset-manifest.json
streamlit_drawable_canvas/frontend/build/index.html
streamlit_drawable_canvas/frontend/build/static/css/main.f0c2de25.chunk.css
streamlit_drawable_canvas/frontend/build/static/css/main.f0c2de25.chunk.css.map
streamlit_drawable_canvas/frontend/build/static/js/2.dacc8892.chunk.js
streamlit_drawable_canvas/frontend/build/static/js/2.dacc8892.chunk.js.LICENSE.txt
streamlit_drawable_canvas/frontend/build/static/js/2.dacc8892.chunk.js.map
streamlit_drawable_canvas/frontend/build/static/js/main.65fb07cb.chunk.js
streamlit_drawable_canvas/frontend/build/static/js/main.65fb07cb.chunk.js.map
streamlit_drawable_canvas/frontend/build/static/js/runtime-main.3def19be.js
streamlit_drawable_canvas/frontend/build/static/js/runtime-main.3def19be.js.map
streamlit_drawable_canvas_fork/__init__.py
streamlit_drawable_canvas_fork/frontend/build/asset-manifest.json
streamlit_drawable_canvas_fork/frontend/build/index.html
streamlit_drawable_canvas_fork/frontend/build/static/css/main.f0c2de25.chunk.css
streamlit_drawable_canvas_fork/frontend/build/static/css/main.f0c2de25.chunk.css.map
streamlit_drawable_canvas_fork/frontend/build/static/js/2.dacc8892.chunk.js
streamlit_drawable_canvas_fork/frontend/build/static/js/2.dacc8892.chunk.js.LICENSE.txt
streamlit_drawable_canvas_fork/frontend/build/static/js/2.dacc8892.chunk.js.map
streamlit_drawable_canvas_fork/frontend/build/static/js/main.65fb07cb.chunk.js
streamlit_drawable_canvas_fork/frontend/build/static/js/main.65fb07cb.chunk.js.map
streamlit_drawable_canvas_fork/frontend/build/static/js/runtime-main.3def19be.js
streamlit_drawable_canvas_fork/frontend/build/static/js/runtime-main.3def19be.js.map
streamlit_drawable_canvas_fork-0.9.4.dist-info/LICENSE
streamlit_drawable_canvas_fork-0.9.4.dist-info/METADATA
streamlit_drawable_canvas_fork-0.9.4.dist-info/WHEEL
streamlit_drawable_canvas_fork-0.9.4.dist-info/top_level.txt
streamlit_drawable_canvas_fork-0.9.4.dist-info/RECORD
