Metadata-Version: 2.2
Name: streamlit-drawable-canvas-fork
Version: 0.9.4
Summary: A Streamlit custom component for a free drawing canvas using Fabric.js.
Home-page: https://github.com/andfanilo/streamlit-drawable-canvas
Author: Fanilo ANDRIANASOLO
Author-email: contact@andfanilo.com
Requires-Python: >=3.6
License-File: LICENSE
Requires-Dist: Pillow
Requires-Dist: numpy
Requires-Dist: streamlit>=0.63
Dynamic: author
Dynamic: author-email
Dynamic: description
Dynamic: description-content-type
Dynamic: home-page
Dynamic: requires-dist
Dynamic: requires-python
Dynamic: summary
